{"title":"submit","uid":"8500f40d44b774e55ea7984dad55b431","slug":"submit","date":"2024-08-04T05:48:55.000Z","updated":"2024-08-04T05:51:00.228Z","comments":true,"path":"api/articles/submit.json","keywords":null,"cover":null,"content":"<h2 id=\"FLowers-Bloom-现已提交\"><a href=\"#FLowers-Bloom-现已提交\" class=\"headerlink\" title=\"FLowers Bloom 现已提交\"></a>FLowers Bloom 现已提交</h2><h2 id=\"FLowers-Bloom-Now-submitted\"><a href=\"#FLowers-Bloom-Now-submitted\" class=\"headerlink\" title=\"FLowers Bloom Now submitted\"></a>FLowers Bloom Now submitted</h2><p>等待中。。。<br>Wating…sS</p>\n","feature":true,"text":"FLowers Bloom 现已提交FLowers Bloom Now submitted等待中。。。Wating…sS ","permalink":"/post/submit","photos":[],"count_time":{"symbolsCount":61,"symbolsTime":"1 mins."},"categories":[],"tags":[{"name":"APP","slug":"APP","count":1,"path":"api/tags/APP.json"}],"toc":"<ol class=\"toc\"><li class=\"toc-item toc-level-2\"><a class=\"toc-link\" href=\"#FLowers-Bloom-%E7%8E%B0%E5%B7%B2%E6%8F%90%E4%BA%A4\"><span class=\"toc-text\">FLowers Bloom 现已提交</span></a></li><li class=\"toc-item toc-level-2\"><a class=\"toc-link\" href=\"#FLowers-Bloom-Now-submitted\"><span class=\"toc-text\">FLowers Bloom Now submitted</span></a></li></ol>","author":{"name":"FLBO","slug":"blog-author","avatar":"https://kuaiji.icu/img/avatar.jpg","link":"/","description":"Flowers Bloom官网","socials":{"github":"","twitter":"","stackoverflow":"","wechat":"","qq":"","weibo":"","zhihu":"","csdn":"","juejin":"","customs":{}}},"mapped":true,"hidden":false,"prev_post":{"title":"prvacy-zh-Hans","uid":"42b9aa94053a481c66082488d2ef4fa6","slug":"prvacy-zh-Hans","date":"2024-08-04T07:14:06.000Z","updated":"2024-08-04T07:16:56.738Z","comments":true,"path":"api/articles/prvacy-zh-Hans.json","keywords":null,"cover":null,"text":"FLowers Bloom 的隐私政策 隐私政策上次更新时间：2024 年 8 月 4 日 本隐私政策描述了我们在您使用服务时收集、使用和披露您的信息的政策和程...","permalink":"/post/prvacy-zh-Hans","photos":[],"count_time":{"symbolsCount":"3.7k","symbolsTime":"3 mins."},"categories":[],"tags":[],"author":{"name":"FLBO","slug":"blog-author","avatar":"https://kuaiji.icu/img/avatar.jpg","link":"/","description":"Flowers Bloom官网","socials":{"github":"","twitter":"","stackoverflow":"","wechat":"","qq":"","weibo":"","zhihu":"","csdn":"","juejin":"","customs":{}}},"feature":true},"next_post":{"title":"FLBO","uid":"d53a205f1d89ebcf0fe7dd37f77ffc93","slug":"FLBO","date":"2024-07-23T16:01:12.000Z","updated":"2024-08-04T03:02:36.505Z","comments":true,"path":"api/articles/FLBO.json","keywords":null,"cover":null,"text":"你好，来宾Welcome FLBO","permalink":"/post/FLBO","photos":[],"count_time":{"symbolsCount":17,"symbolsTime":"1 mins."},"categories":[],"tags":[],"author":{"name":"FLBO","slug":"blog-author","avatar":"https://kuaiji.icu/img/avatar.jpg","link":"/","description":"Flowers Bloom官网","socials":{"github":"","twitter":"","stackoverflow":"","wechat":"","qq":"","weibo":"","zhihu":"","csdn":"","juejin":"","customs":{}}},"feature":true}}