{"name":"疫情调查","slug":"疫情调查","count":1,"postlist":[{"title":"疫情调查","uid":"016d5ed35dcdd6d2d3b2a1fa2fd3816d","slug":"疫情调查","date":"2021-08-05T11:04:04.000Z","updated":"2021-08-10T16:00:40.447Z","comments":true,"path":"api/articles/疫情调查.json","keywords":null,"cover":"https://cdn.jsdelivr.net/gh/sky20681/sky20681/2021/05/30/4kbizhi/13.jpg","text":"我就搞不懂了啊最近，老是接到电话询问我的姓名住址，问我七月份去哪了我就十分纳闷不是有行程大数据卡吗每次进出大型政府公共场所不是扫了“进”的二维码了吗？为什么还是不厌其烦的打电话过来核实，不过还好，现在不是随便一个私人电话张口就开始查户口。不仅预约还用上了人工智能语音。 下面谈一谈...","link":"","photos":[],"count_time":{"symbolsCount":173,"symbolsTime":"1 mins."},"categories":[{"name":"其他","slug":"其他","count":29,"path":"api/categories/其他.json"}],"tags":[{"name":"疫情调查","slug":"疫情调查","count":1,"path":"api/tags/疫情调查.json"}],"author":{"name":"花开","slug":"blog-author","avatar":"https://cdn.jsdelivr.net/gh/sky20681/sky20681/medias/avatar.jpg","link":"/","description":"我不会向暴力犯罪屈服。","socials":{"github":"https://github.com/","twitter":"https://twitter.com/","stackoverflow":"https://stackoverflow.com","wechat":"","qq":"","weibo":"https://weibo.com/","zhihu":"https://www.zhihu.com/","csdn":"https://blog.csdn.net/","juejin":"https://juejin.cn/","customs":{}}}}]}